{
  "totalLength": 980,
  "totalLength2": 980,
  "headerLength": 92,
  "scriptNumber": 23,
  "unk20": 4,
  "parentNumber": -1,
  "scriptFlags": 0,
  "unk42": 0,
  "castID": 196632,
  "factoryNameID": -1,
  "handlerVectorsCount": 9,
  "handlerVectorsOffset": 962,
  "handlerVectorsSize": 386,
  "propertiesCount": 5,
  "propertiesOffset": 92,
  "globalsCount": 1,
  "globalsOffset": 102,
  "handlersCount": 8,
  "handlersOffset": 104,
  "literalsCount": 6,
  "literalsOffset": 816,
  "literalsDataCount": 98,
  "literalsDataOffset": 864,
  "propertyNameIDs": [
    508,
    525,
    404,
    527,
    408
  ],
  "globalNameIDs": [
    439
  ],
  "handlers": [
    {
      "nameID": 504,
      "vectorPos": 65535,
      "compiledLen": 20,
      "compiledOffset": 472,
      "argumentCount": 1,
      "argumentOffset": 492,
      "localsCount": 0,
      "localsOffset": 494,
      "globalsCount": 0,
      "globalsOffset": 102,
      "unknown1": 94,
      "unknown2": 5,
      "lineCount": 2,
      "lineOffset": 494,
      "stackHeight": 2
    },
    {
      "nameID": 505,
      "vectorPos": 7,
      "compiledLen": 61,
      "compiledOffset": 496,
      "argumentCount": 1,
      "argumentOffset": 558,
      "localsCount": 0,
      "localsOffset": 560,
      "globalsCount": 0,
      "globalsOffset": 102,
      "unknown1": 158,
      "unknown2": 10,
      "lineCount": 7,
      "lineOffset": 560,
      "stackHeight": 4
    },
    {
      "nameID": 515,
      "vectorPos": 1,
      "compiledLen": 24,
      "compiledOffset": 568,
      "argumentCount": 1,
      "argumentOffset": 592,
      "localsCount": 0,
      "localsOffset": 594,
      "globalsCount": 0,
      "globalsOffset": 102,
      "unknown1": 348,
      "unknown2": 20,
      "lineCount": 3,
      "lineOffset": 594,
      "stackHeight": 5
    },
    {
      "nameID": 506,
      "vectorPos": 8,
      "compiledLen": 36,
      "compiledOffset": 598,
      "argumentCount": 1,
      "argumentOffset": 634,
      "localsCount": 0,
      "localsOffset": 636,
      "globalsCount": 0,
      "globalsOffset": 102,
      "unknown1": 456,
      "unknown2": 26,
      "lineCount": 5,
      "lineOffset": 636,
      "stackHeight": 2
    },
    {
      "nameID": 401,
      "vectorPos": 65535,
      "compiledLen": 23,
      "compiledOffset": 642,
      "argumentCount": 1,
      "argumentOffset": 666,
      "localsCount": 0,
      "localsOffset": 668,
      "globalsCount": 0,
      "globalsOffset": 102,
      "unknown1": 587,
      "unknown2": 34,
      "lineCount": 3,
      "lineOffset": 668,
      "stackHeight": 3
    },
    {
      "nameID": 402,
      "vectorPos": 65535,
      "compiledLen": 23,
      "compiledOffset": 672,
      "argumentCount": 1,
      "argumentOffset": 696,
      "localsCount": 0,
      "localsOffset": 698,
      "globalsCount": 0,
      "globalsOffset": 102,
      "unknown1": 686,
      "unknown2": 40,
      "lineCount": 3,
      "lineOffset": 698,
      "stackHeight": 3
    },
    {
      "nameID": 400,
      "vectorPos": 65535,
      "compiledLen": 8,
      "compiledOffset": 702,
      "argumentCount": 1,
      "argumentOffset": 710,
      "localsCount": 0,
      "localsOffset": 712,
      "globalsCount": 0,
      "globalsOffset": 102,
      "unknown1": 771,
      "unknown2": 46,
      "lineCount": 1,
      "lineOffset": 712,
      "stackHeight": 2
    },
    {
      "nameID": 507,
      "vectorPos": 65535,
      "compiledLen": 94,
      "compiledOffset": 714,
      "argumentCount": 0,
      "argumentOffset": 808,
      "localsCount": 1,
      "localsOffset": 808,
      "globalsCount": 0,
      "globalsOffset": 102,
      "unknown1": 829,
      "unknown2": 50,
      "lineCount": 5,
      "lineOffset": 810,
      "stackHeight": 9
    }
  ],
  "literals": [
    {
      "type": 1,
      "offset": 0,
      "value": "shop_button_deactivated"
    },
    {
      "type": 1,
      "offset": 28,
      "value": "shop_button"
    },
    {
      "type": 1,
      "offset": 44,
      "value": ""
    },
    {
      "type": 1,
      "offset": 50,
      "value": "Item Name"
    },
    {
      "type": 1,
      "offset": 64,
      "value": "Item Price"
    },
    {
      "type": 1,
      "offset": 80,
      "value": "3D World Name"
    }
  ]
}
